{
    "period_names": [
        "period_1",
        "period_2",
        "period_3",
        "period_4",
        "period_5",
        "period_6",
        "period_7",
        "period_8",
        "period_9",
        "period_10",
        "period_11",
        "period_12",
        "period_13",
        "period_14",
        "period_15",
        "period_16",
        "period_17",
        "period_18",
        "period_19",
        "period_20",
        "period_21",
        "period_22",
        "period_23",
        "period_24",
        "period_25",
        "period_26",
        "period_27",
        "period_28",
        "period_29",
        "period_30",
        "period_31",
        "period_32",
        "period_33",
        "period_34",
        "period_35",
        "period_36",
        "period_37",
        "period_38",
        "period_39",
        "period_40",
        "period_41",
        "period_42",
        "period_43",
        "period_44",
        "period_45",
        "period_46",
        "period_47",
        "period_48",
        "period_49",
        "period_50",
        "period_51",
        "period_52",
        "period_53",
        "period_54",
        "period_55",
        "period_56",
        "period_57",
        "period_58",
        "period_59",
        "period_60",
        "period_61",
        "period_62",
        "period_63",
        "period_64"
    ],
    "num_stations": {
        "MS": [
            0,
            0,
            0,
            0,
            0,
            0,
            0,
            0,
            0,
            0,
            0,
            0,
            0,
            0,
            0,
            0,
            0,
            0,
            0,
            0,
            0,
            0,
            0,
            0,
            0,
            0,
            0,
            0,
            0,
            0,
            0,
            0,
            0,
            0,
            0,
            0,
            0,
            0,
            0,
            0,
            0,
            0,
            0,
            0,
            0,
            0,
            0,
            0,
            0,
            0,
            0,
            0,
            0,
            0,
            0,
            0,
            0,
            0,
            0,
            0,
            0,
            0,
            0,
            0
        ],
        "MLS": [
            4,
            4,
            4,
            3,
            4,
            4,
            4,
            4,
            4,
            5,
            5,
            5,
            5,
            4,
            5,
            5,
            4,
            4,
            4,
            5,
            6,
            5,
            5,
            5,
            6,
            5,
            3,
            3,
            5,
            6,
            4,
            5,
            6,
            4,
            4,
            5,
            6,
            5,
            2,
            5,
            3,
            4,
            5,
            6,
            6,
            5,
            5,
            6,
            6,
            6,
            5,
            5,
            2,
            6,
            2,
            8,
            4,
            3,
            3,
            4,
            5,
            2,
            3,
            2
        ],
        "RLS": [
            4,
            4,
            4,
            3,
            3,
            1,
            1,
            1,
            1,
            2,
            2,
            2,
            2,
            2,
            2,
            2,
            2,
            2,
            2,
            1,
            1,
            1,
            1,
            2,
            1,
            1,
            1,
            1,
            1,
            2,
            2,
            1,
            1,
            1,
            1,
            1,
            1,
            1,
            1,
            2,
            2,
            2,
            1,
            2,
            3,
            2,
            2,
            2,
            2,
            1,
            1,
            1,
            1,
            1,
            0,
            0,
            0,
            0,
            0,
            1,
            1,
            1,
            1,
            1
        ],
        "AS": [
            4,
            4,
            4,
            4,
            4,
            4,
            4,
            4,
            4,
            4,
            4,
            4,
            4,
            4,
            4,
            4,
            4,
            4,
            4,
            4,
            4,
            4,
            4,
            4,
            4,
            4,
            4,
            4,
            4,
            4,
            4,
            4,
            4,
            4,
            4,
            4,
            5,
            5,
            5,
            5,
            5,
            5,
            5,
            5,
            5,
            5,
            5,
            5,
            5,
            5,
            5,
            5,
            5,
            5,
            5,
            5,
            5,
            5,
            5,
            5,
            5,
            5,
            5,
            5
        ]
    },
    "utilization_stations": {
        "MS": [
            "-",
            "-",
            "-",
            "-",
            "-",
            "-",
            "-",
            "-",
            "-",
            "-",
            "-",
            "-",
            "-",
            "-",
            "-",
            "-",
            "-",
            "-",
            "-",
            "-",
            "-",
            "-",
            "-",
            "-",
            "-",
            "-",
            "-",
            "-",
            "-",
            "-",
            "-",
            "-",
            "-",
            "-",
            "-",
            "-",
            "-",
            "-",
            "-",
            "-",
            "-",
            "-",
            "-",
            "-",
            "-",
            "-",
            "-",
            "-",
            "-",
            "-",
            "-",
            "-",
            "-",
            "-",
            "-",
            "-",
            "-",
            "-",
            "-",
            "-",
            "-",
            "-",
            "-",
            "-"
        ],
        "MLS": [
            0.353,
            0.651,
            0.992,
            0.996,
            0.992,
            0.987,
            0.991,
            0.988,
            0.99,
            0.99,
            0.99,
            0.988,
            0.989,
            0.992,
            0.987,
            0.987,
            0.991,
            0.992,
            0.994,
            0.987,
            0.981,
            0.985,
            0.982,
            0.991,
            0.981,
            0.985,
            0.921,
            0.993,
            0.984,
            0.984,
            0.992,
            0.982,
            0.976,
            0.988,
            0.989,
            0.981,
            0.982,
            0.984,
            0.999,
            0.991,
            0.996,
            0.992,
            0.986,
            0.988,
            0.989,
            0.99,
            0.99,
            0.985,
            0.987,
            0.983,
            0.986,
            0.986,
            0.889,
            0.983,
            0.739,
            0.972,
            0.987,
            0.993,
            0.877,
            0.942,
            0.986,
            0.852,
            0.989,
            0.997
        ],
        "RLS": [
            0.346,
            0.627,
            0.925,
            0.937,
            0.897,
            0.943,
            0.905,
            0.912,
            0.909,
            0.864,
            0.857,
            0.88,
            0.86,
            0.87,
            0.854,
            0.857,
            0.9,
            0.891,
            0.883,
            0.883,
            0.838,
            0.866,
            0.895,
            0.864,
            0.854,
            0.889,
            0.87,
            0.93,
            0.884,
            0.827,
            0.886,
            0.888,
            0.859,
            0.905,
            0.904,
            0.888,
            0.88,
            0.908,
            0.984,
            0.872,
            0.926,
            0.896,
            0.901,
            0.857,
            0.843,
            0.872,
            0.864,
            0.852,
            0.861,
            0.876,
            0.899,
            0.899,
            0.873,
            0.885,
            "-",
            "-",
            "-",
            "-",
            "-",
            0.887,
            0.909,
            0.83,
            0.943,
            0.976
        ],
        "AS": [
            0.206,
            0.406,
            0.601,
            0.593,
            0.64,
            0.603,
            0.597,
            0.601,
            0.574,
            0.615,
            0.612,
            0.636,
            0.621,
            0.606,
            0.64,
            0.63,
            0.601,
            0.6,
            0.606,
            0.616,
            0.638,
            0.632,
            0.629,
            0.638,
            0.628,
            0.614,
            0.496,
            0.549,
            0.626,
            0.648,
            0.611,
            0.625,
            0.63,
            0.607,
            0.601,
            0.627,
            0.607,
            0.593,
            0.39,
            0.575,
            0.506,
            0.561,
            0.573,
            0.596,
            0.61,
            0.591,
            0.566,
            0.605,
            0.601,
            0.601,
            0.577,
            0.569,
            0.334,
            0.6,
            0.259,
            0.64,
            0.527,
            0.439,
            0.415,
            0.496,
            0.576,
            0.329,
            0.474,
            0.407
        ],
        "all_stations": [
            0.302,
            0.561,
            0.839,
            0.817,
            0.838,
            0.811,
            0.806,
            0.807,
            0.796,
            0.831,
            0.828,
            0.84,
            0.832,
            0.813,
            0.837,
            0.833,
            0.816,
            0.815,
            0.817,
            0.828,
            0.843,
            0.832,
            0.832,
            0.839,
            0.841,
            0.827,
            0.702,
            0.763,
            0.831,
            0.846,
            0.819,
            0.83,
            0.839,
            0.809,
            0.807,
            0.83,
            0.817,
            0.799,
            0.616,
            0.798,
            0.737,
            0.778,
            0.791,
            0.817,
            0.822,
            0.804,
            0.793,
            0.818,
            0.819,
            0.815,
            0.792,
            0.789,
            0.54,
            0.815,
            0.396,
            0.844,
            0.731,
            0.647,
            0.588,
            0.713,
            0.793,
            0.522,
            0.698,
            0.625
        ]
    }
}